mlvtrans/__init__.py
mlvtrans/main.py
mlvtrans-0.1.1.dist-info/LICENSE
mlvtrans-0.1.1.dist-info/METADATA
mlvtrans-0.1.1.dist-info/WHEEL
mlvtrans-0.1.1.dist-info/entry_points.txt
mlvtrans-0.1.1.dist-info/top_level.txt
mlvtrans-0.1.1.dist-info/RECORD
