Metadata-Version: 2.2
Name: mlvtrans
Version: 0.1.1
Summary: mlvtrans: construct a compatible symplectic basis and transversal phase-type gates for self-dual CSS codes
Home-page: https://github.com/yugotakada/mlvtrans.git
Author: yugotakada
Author-email: yugo.takada1@gmail.com
License: MIT License
Classifier: Programming Language :: Python :: 3
Classifier: License :: OSI Approved :: MIT License
License-File: LICENSE
Requires-Dist: numpy
Requires-Dist: stim
Dynamic: author
Dynamic: author-email
Dynamic: classifier
Dynamic: description
Dynamic: description-content-type
Dynamic: home-page
Dynamic: license
Dynamic: requires-dist
Dynamic: summary
